{"tile": {"0;78": [[[0, 10064], 53, "grass_top"], [[16, 10064], 53, "grass_top"], [[32, 10064], 53, "grass_top"], [[48, 10064], 53, "grass_top"], [[64, 10064], 53, "grass_top"], [[80, 10064], 53, "grass_top"], [[96, 10064], 53, "grass_top"], [[112, 10064], 53, "grass_top"]], "1;78": [[[128, 10064], 53, "grass_top"], [[144, 10064], 53, "grass_top"], [[160, 10064], 53, "grass_top"], [[176, 10064], 53, "grass_top"]]}, "object": [[[86, 10012], 82, "trap_suspended"]], "entity": [[[32, 10048], 90, "herochar"]], "variable": {}}